autofeatureselect/__init__.py
autofeatureselect/filters.py
autofeatureselect/model_wrappers.py
smartfeatureselectml-0.1.6.dist-info/licenses/LICENSE
smartfeatureselectml-0.1.6.dist-info/METADATA
smartfeatureselectml-0.1.6.dist-info/WHEEL
smartfeatureselectml-0.1.6.dist-info/top_level.txt
smartfeatureselectml-0.1.6.dist-info/RECORD
