Metadata-Version: 2.4
Name: smartfeatureselectml
Version: 0.1.6
Summary: A Python package for automated feature selection in ML workflows.
Home-page: https://github.com/SHREENIDHI1903/AutoFeatureSelect
Author: Shreenidhi T H
Author-email: shreenidhi1903@example.com
Classifier: Programming Language :: Python :: 3
Classifier: License :: OSI Approved :: MIT License
Classifier: Operating System :: OS Independent
Requires-Python: >=3.7
License-File: LICENSE
Requires-Dist: numpy
Requires-Dist: pandas
Requires-Dist: scikit-learn
Requires-Dist: xgboost
Requires-Dist: shap
Requires-Dist: statsmodels
Dynamic: author
Dynamic: author-email
Dynamic: classifier
Dynamic: description
Dynamic: description-content-type
Dynamic: home-page
Dynamic: license-file
Dynamic: requires-dist
Dynamic: requires-python
Dynamic: summary
